{
  "acquistion_notes": "Testamentarisk gave fra Hans Gude",
  "descriptive_date": "6. august 1857",
  "digital_item_created_at": "2014-02-04T03:58:29.336773",
  "digitalt_museum_id": "011042513727",
  "digitalt_museum_link": "https://digitaltmuseum.org/011042513727",
  "from_date": "1857-08-06",
  "locations": {
    "depicted_location": [
      {
        "coordinates": "50.4133909, 7.272189900000058",
        "human_name": "Laacher See, Rhineland-Palatinate, Germany",
        "place_names": [
          {
            "level": 1,
            "name": "Germany",
            "place_type": "country"
          },
          {
            "level": 3,
            "name": "Rhineland-Palatinate",
            "place_type": "area"
          },
          {
            "level": 4,
            "name": "Laacher See",
            "place_type": "specific_area"
          }
        ]
      }
    ]
  },
  "material_comment": "Blyant p\u00e5 papir",
  "materials": [
    "paper"
  ],
  "measurements": {
    "main_object": {
      "height": 434.0,
      "height_unit": "mm",
      "width": 295.0,
      "width_unit": "mm"
    }
  },
  "nasjonalmuseet_link": "https://www.nasjonalmuseet.no/en/collection/object/NG.K_H.B.06511-001",
  "national_museum_norway_artwork_id": "NG.K&H.B.06511-001",
  "picture": {
    "direct_image_link": "https://ms01.nasjonalmuseet.no/api/objects/download?filename=74680.tif&size=full",
    "height": 3000,
    "index": 74680,
    "width": 2090
  },
  "subjects": [],
  "techniques": [
    "pencil"
  ],
  "titles": {
    "nor": {
      "current": [
        "Trestudie ved Laacher See"
      ]
    }
  },
  "to_date": "1857-08-06",
  "uuid": "F1A12493-F068-471F-967F-FD3D9BD5E6CC"
}